<?xml version="1.0" encoding="UTF-8"?>
<con:soapui-project id="3bdaaf90-3be5-44b5-9308-b580d7552c38" activeEnvironment="Default" name="IT26g2018-Zuber-Ana" resourceRoot="${projectDir}" soapui-version="5.6.0" abortOnError="false" runType="SEQUENTIAL" xmlns:con="http://eviware.com/soapui/config"><con:settings/><con:interface xsi:type="con:RestService" id="9d703dda-ee80-4ee1-8abc-4a4f94143501" wadlVersion="http://wadl.dev.java.net/2009/02" name="http://localhost:8084" type="rest" xmlns:xsi="http://www.w3.org/2001/XMLSchema-instance"><con:settings/><con:definitionCache type="TEXT" rootPart=""/><con:endpoints><con:endpoint>http://localhost:8084</con:endpoint></con:endpoints><con:resource name="Kredit Get All" path="/kredit" id="e777e981-18ad-4a76-9998-0da6ce54615c"><con:settings/><con:parameters/><con:method name="Get All" id="37008de6-4c59-4606-9a12-1a3bfd9dec25" method="GET"><con:settings/><con:parameters/><con:representation type="RESPONSE"><con:mediaType>application/json</con:mediaType><con:status>200</con:status><con:params/><con:element>Response</con:element></con:representation><con:representation type="RESPONSE"><con:mediaType xsi:nil="true"/><con:status>0</con:status><con:params/><con:element>data</con:element></con:representation><con:request name="Kredit Get All" id="55b5b7b4-ab41-4887-bc57-ca7d68b59919" mediaType="application/json"><con:settings><con:setting id="com.eviware.soapui.impl.wsdl.WsdlRequest@request-headers">&lt;xml-fragment/></con:setting></con:settings><con:endpoint>http://localhost:8084</con:endpoint><con:request/><con:originalUri>http://localhost/kredit</con:originalUri><con:credentials><con:authType>No Authorization</con:authType></con:credentials><con:jmsConfig JMSDeliveryMode="PERSISTENT"/><con:jmsPropertyConfig/><con:parameters/></con:request></con:method></con:resource><con:resource name="Kredit Get By ID" path="/kredit/{id}" id="b1902b8a-682d-4b88-a303-5da0b9e7edf1"><con:settings/><con:parameters><con:parameter><con:name>id</con:name><con:value>1</con:value><con:style>TEMPLATE</con:style><con:default>1</con:default></con:parameter></con:parameters><con:method name="Method Get By ID" id="ada7ab53-82bf-416f-8210-b48c9d6bb23d" method="GET"><con:settings/><con:parameters/><con:representation type="RESPONSE"><con:mediaType>application/json</con:mediaType><con:status>200</con:status><con:params/><con:element xmlns:ns="http://localhost/kredit/1">ns:Response</con:element></con:representation><con:request name="Kredit Get By ID" id="17313365-ee72-4b2a-bffd-1db42ec4582e" mediaType="application/json"><con:settings><con:setting id="com.eviware.soapui.impl.wsdl.WsdlRequest@request-headers">&lt;xml-fragment/></con:setting></con:settings><con:endpoint>http://localhost:8084</con:endpoint><con:request/><con:originalUri>http://localhost/kredit/1</con:originalUri><con:credentials><con:authType>No Authorization</con:authType></con:credentials><con:jmsConfig JMSDeliveryMode="PERSISTENT"/><con:jmsPropertyConfig/><con:parameters><entry key="id" value="1" xmlns="http://eviware.com/soapui/config"/></con:parameters><con:parameterOrder><con:entry>id</con:entry></con:parameterOrder></con:request></con:method></con:resource><con:resource name="Kredit Get By Naziv" path="/kreditNaziv/{naziv}" id="b1902b8a-682d-4b88-a303-5da0b9e7edf1"><con:settings/><con:parameters><con:parameter><con:name>id</con:name><con:value>1</con:value><con:style>TEMPLATE</con:style><con:default>1</con:default></con:parameter><con:parameter><con:name>naziv</con:name><con:style>TEMPLATE</con:style></con:parameter></con:parameters><con:method name="Method Get By Naziv" id="ada7ab53-82bf-416f-8210-b48c9d6bb23d" method="GET"><con:settings/><con:parameters/><con:representation type="RESPONSE"><con:mediaType>application/json</con:mediaType><con:status>200</con:status><con:params/><con:element xmlns:ns="http://localhost/kredit/1">ns:Response</con:element></con:representation><con:request name="Kredit Get By Naziv" id="17313365-ee72-4b2a-bffd-1db42ec4582e" mediaType="application/json"><con:settings><con:setting id="com.eviware.soapui.impl.wsdl.WsdlRequest@request-headers">&lt;xml-fragment/></con:setting></con:settings><con:endpoint>http://localhost:8084</con:endpoint><con:request/><con:originalUri>http://localhost/kredit/1</con:originalUri><con:credentials><con:authType>No Authorization</con:authType></con:credentials><con:jmsConfig JMSDeliveryMode="PERSISTENT"/><con:jmsPropertyConfig/><con:parameters>
  <con:entry key="naziv" value="Stambeni"/>
  <con:entry key="id" value="1"/>
</con:parameters><con:parameterOrder><con:entry>id</con:entry><con:entry>naziv</con:entry></con:parameterOrder></con:request></con:method></con:resource><con:resource name="Kredit Insert" path="/kredit" id="e777e981-18ad-4a76-9998-0da6ce54615c"><con:settings/><con:parameters/><con:method name="Method Insert" id="37008de6-4c59-4606-9a12-1a3bfd9dec25" method="POST"><con:settings/><con:parameters/><con:representation type="RESPONSE"><con:mediaType>application/json</con:mediaType><con:status>200</con:status><con:params/><con:element>Response</con:element></con:representation><con:representation type="FAULT"><con:mediaType>application/json</con:mediaType><con:status>500</con:status><con:params/><con:element xmlns:kred="http://localhost/kredit">kred:Fault</con:element></con:representation><con:representation type="REQUEST"><con:mediaType>application/json</con:mediaType><con:params/></con:representation><con:representation type="RESPONSE"><con:mediaType xsi:nil="true"/><con:status>200</con:status><con:params/><con:element>data</con:element></con:representation><con:representation type="RESPONSE"><con:mediaType xsi:nil="true"/><con:status>200</con:status><con:params/><con:element>data</con:element></con:representation><con:representation type="RESPONSE"><con:mediaType xsi:nil="true"/><con:status>200</con:status><con:params/><con:element>data</con:element></con:representation><con:representation type="RESPONSE"><con:mediaType xsi:nil="true"/><con:status>200</con:status><con:params/><con:element>data</con:element></con:representation><con:representation type="RESPONSE"><con:mediaType xsi:nil="true"/><con:status>200</con:status><con:params/><con:element>data</con:element></con:representation><con:representation type="RESPONSE"><con:mediaType xsi:nil="true"/><con:status>200</con:status><con:params/><con:element>data</con:element></con:representation><con:representation type="RESPONSE"><con:mediaType xsi:nil="true"/><con:status>200</con:status><con:params/><con:element>data</con:element></con:representation><con:request name="Kredit Insert" id="55b5b7b4-ab41-4887-bc57-ca7d68b59919" mediaType="application/json" postQueryString="false"><con:settings><con:setting id="com.eviware.soapui.impl.wsdl.WsdlRequest@request-headers">&lt;xml-fragment/></con:setting></con:settings><con:endpoint>http://localhost:8084</con:endpoint><con:request>{
      "id": 46,
      "naziv": "Insert Kredit",
      "opis": "Insert Kredit",
      "oznaka": "123"
   }</con:request><con:originalUri>http://localhost/kredit</con:originalUri><con:credentials><con:authType>No Authorization</con:authType></con:credentials><con:jmsConfig JMSDeliveryMode="PERSISTENT"/><con:jmsPropertyConfig/><con:parameters/></con:request></con:method></con:resource><con:resource name="Kredit Update" path="/kredit" id="e777e981-18ad-4a76-9998-0da6ce54615c"><con:settings/><con:parameters/><con:method name="Method Update" id="37008de6-4c59-4606-9a12-1a3bfd9dec25" method="PUT"><con:settings/><con:parameters/><con:representation type="RESPONSE"><con:mediaType>application/json</con:mediaType><con:status>200</con:status><con:params/><con:element>Response</con:element></con:representation><con:representation type="FAULT"><con:mediaType>application/json</con:mediaType><con:status>500</con:status><con:params/><con:element xmlns:kred="http://localhost/kredit">kred:Fault</con:element></con:representation><con:representation type="REQUEST"><con:mediaType>application/json</con:mediaType><con:params/></con:representation><con:representation type="RESPONSE"><con:mediaType xsi:nil="true"/><con:status>200</con:status><con:params/><con:element>data</con:element></con:representation><con:representation type="RESPONSE"><con:mediaType xsi:nil="true"/><con:status>200</con:status><con:params/><con:element>data</con:element></con:representation><con:representation type="RESPONSE"><con:mediaType xsi:nil="true"/><con:status>200</con:status><con:params/><con:element>data</con:element></con:representation><con:representation type="FAULT"><con:mediaType xsi:nil="true"/><con:status>409</con:status><con:params/><con:element>data</con:element></con:representation><con:representation type="FAULT"><con:mediaType xsi:nil="true"/><con:status>409</con:status><con:params/><con:element>data</con:element></con:representation><con:representation type="FAULT"><con:mediaType xsi:nil="true"/><con:status>409</con:status><con:params/><con:element>data</con:element></con:representation><con:representation type="FAULT"><con:mediaType xsi:nil="true"/><con:status>409</con:status><con:params/><con:element>data</con:element></con:representation><con:representation type="RESPONSE"><con:mediaType xsi:nil="true"/><con:status>200</con:status><con:params/><con:element>data</con:element></con:representation><con:representation type="RESPONSE"><con:mediaType xsi:nil="true"/><con:status>200</con:status><con:params/><con:element>data</con:element></con:representation><con:request name="Kredit Update" id="55b5b7b4-ab41-4887-bc57-ca7d68b59919" mediaType="application/json" postQueryString="false"><con:settings><con:setting id="com.eviware.soapui.impl.wsdl.WsdlRequest@request-headers">&lt;xml-fragment/></con:setting></con:settings><con:endpoint>http://localhost:8084</con:endpoint><con:request> {
      "id": -100,
      "naziv": "Update Kredit",
      "opis": "Update Kredit",
      "oznaka": "123"
   }</con:request><con:originalUri>http://localhost/kredit</con:originalUri><con:credentials><con:authType>No Authorization</con:authType></con:credentials><con:jmsConfig JMSDeliveryMode="PERSISTENT"/><con:jmsPropertyConfig/><con:parameters/><con:parameterOrder/></con:request></con:method></con:resource><con:resource name="Kredit Delete" path="/kredit/{id}" id="e777e981-18ad-4a76-9998-0da6ce54615c"><con:settings/><con:parameters><con:parameter><con:name>id</con:name><con:value>-46</con:value><con:style>TEMPLATE</con:style><con:default>-46</con:default></con:parameter></con:parameters><con:method name="Method Delete" id="37008de6-4c59-4606-9a12-1a3bfd9dec25" method="DELETE"><con:settings/><con:parameters/><con:representation type="RESPONSE"><con:mediaType>application/json</con:mediaType><con:status>200</con:status><con:params/><con:element>Response</con:element></con:representation><con:representation type="FAULT"><con:mediaType>application/json</con:mediaType><con:status>500</con:status><con:params/><con:element xmlns:kred="http://localhost/kredit">kred:Fault</con:element></con:representation><con:representation type="REQUEST"><con:mediaType>application/json</con:mediaType><con:params/></con:representation><con:representation type="RESPONSE"><con:mediaType xsi:nil="true"/><con:status>200</con:status><con:params/><con:element>data</con:element></con:representation><con:representation type="RESPONSE"><con:mediaType xsi:nil="true"/><con:status>200</con:status><con:params/><con:element>data</con:element></con:representation><con:representation type="RESPONSE"><con:mediaType xsi:nil="true"/><con:status>200</con:status><con:params/><con:element>data</con:element></con:representation><con:representation type="RESPONSE"><con:mediaType xsi:nil="true"/><con:status>200</con:status><con:params/><con:element>data</con:element></con:representation><con:representation type="RESPONSE"><con:mediaType xsi:nil="true"/><con:status>200</con:status><con:params/><con:element>data</con:element></con:representation><con:representation type="RESPONSE"><con:mediaType xsi:nil="true"/><con:status>200</con:status><con:params/><con:element>data</con:element></con:representation><con:representation type="RESPONSE"><con:mediaType xsi:nil="true"/><con:status>200</con:status><con:params/><con:element>data</con:element></con:representation><con:representation type="RESPONSE"><con:mediaType xsi:nil="true"/><con:status>200</con:status><con:params/><con:element>data</con:element></con:representation><con:representation type="RESPONSE"><con:mediaType xsi:nil="true"/><con:status>200</con:status><con:params/><con:element>data</con:element></con:representation><con:representation type="RESPONSE"><con:mediaType xsi:nil="true"/><con:status>200</con:status><con:params/><con:element>data</con:element></con:representation><con:representation type="RESPONSE"><con:mediaType xsi:nil="true"/><con:status>200</con:status><con:params/><con:element>data</con:element></con:representation><con:representation type="RESPONSE"><con:mediaType xsi:nil="true"/><con:status>200</con:status><con:params/><con:element>data</con:element></con:representation><con:request name="Kredit Delete" id="55b5b7b4-ab41-4887-bc57-ca7d68b59919" mediaType="application/json" postQueryString="false"><con:settings><con:setting id="com.eviware.soapui.impl.wsdl.WsdlRequest@request-headers">&lt;xml-fragment/></con:setting></con:settings><con:endpoint>http://localhost:8084</con:endpoint><con:request/><con:originalUri>http://localhost/kredit</con:originalUri><con:credentials><con:authType>No Authorization</con:authType></con:credentials><con:jmsConfig JMSDeliveryMode="PERSISTENT"/><con:jmsPropertyConfig/><con:parameters><entry key="id" value="-100" xmlns="http://eviware.com/soapui/config"/></con:parameters><con:parameterOrder><con:entry>id</con:entry></con:parameterOrder></con:request></con:method></con:resource><con:resource name="Tip Racuna Get All" path="/tipRacuna" id="e777e981-18ad-4a76-9998-0da6ce54615c"><con:settings/><con:parameters/><con:method name="Get All" id="37008de6-4c59-4606-9a12-1a3bfd9dec25" method="GET"><con:settings/><con:parameters/><con:representation type="RESPONSE"><con:mediaType>application/json</con:mediaType><con:status>200</con:status><con:params/><con:element>Response</con:element></con:representation><con:representation type="RESPONSE"><con:mediaType xsi:nil="true"/><con:status>0</con:status><con:params/><con:element>data</con:element></con:representation><con:request name="Tip Racuna Get All" id="55b5b7b4-ab41-4887-bc57-ca7d68b59919" mediaType="application/json"><con:settings><con:setting id="com.eviware.soapui.impl.wsdl.WsdlRequest@request-headers">&lt;xml-fragment/></con:setting></con:settings><con:endpoint>http://localhost:8084</con:endpoint><con:request/><con:originalUri>http://localhost/kredit</con:originalUri><con:credentials><con:authType>No Authorization</con:authType></con:credentials><con:jmsConfig JMSDeliveryMode="PERSISTENT"/><con:jmsPropertyConfig/><con:parameters/></con:request></con:method></con:resource><con:resource name="Tip Racuna Get By ID" path="/tipRacuna/{id}" id="b1902b8a-682d-4b88-a303-5da0b9e7edf1"><con:settings/><con:parameters><con:parameter><con:name>id</con:name><con:value>1</con:value><con:style>TEMPLATE</con:style><con:default>1</con:default></con:parameter></con:parameters><con:method name="Method Get By ID" id="ada7ab53-82bf-416f-8210-b48c9d6bb23d" method="GET"><con:settings/><con:parameters/><con:representation type="RESPONSE"><con:mediaType>application/json</con:mediaType><con:status>200</con:status><con:params/><con:element xmlns:ns="http://localhost/kredit/1">ns:Response</con:element></con:representation><con:request name="Tip RacunaGet By ID" id="17313365-ee72-4b2a-bffd-1db42ec4582e" mediaType="application/json"><con:settings><con:setting id="com.eviware.soapui.impl.wsdl.WsdlRequest@request-headers">&lt;xml-fragment/></con:setting></con:settings><con:endpoint>http://localhost:8084</con:endpoint><con:request/><con:originalUri>http://localhost/kredit/1</con:originalUri><con:credentials><con:authType>No Authorization</con:authType></con:credentials><con:jmsConfig JMSDeliveryMode="PERSISTENT"/><con:jmsPropertyConfig/><con:parameters><entry key="id" value="1" xmlns="http://eviware.com/soapui/config"/></con:parameters><con:parameterOrder><con:entry>id</con:entry></con:parameterOrder></con:request></con:method></con:resource><con:resource name="Tip Racuna Get By Naziv" path="/tipRacunaNaziv/{naziv}" id="b1902b8a-682d-4b88-a303-5da0b9e7edf1"><con:settings/><con:parameters><con:parameter><con:name>naziv</con:name><con:style>TEMPLATE</con:style></con:parameter></con:parameters><con:method name="Method Get By Naziv" id="ada7ab53-82bf-416f-8210-b48c9d6bb23d" method="GET"><con:settings/><con:parameters/><con:representation type="RESPONSE"><con:mediaType>application/json</con:mediaType><con:status>200</con:status><con:params/><con:element xmlns:ns="http://localhost/kredit/1">ns:Response</con:element></con:representation><con:request name="Tip Racuna Get By Naziv" id="17313365-ee72-4b2a-bffd-1db42ec4582e" mediaType="application/json"><con:settings><con:setting id="com.eviware.soapui.impl.wsdl.WsdlRequest@request-headers">&lt;xml-fragment/></con:setting></con:settings><con:endpoint>http://localhost:8084</con:endpoint><con:request/><con:originalUri>http://localhost/kredit/1</con:originalUri><con:credentials><con:authType>No Authorization</con:authType></con:credentials><con:jmsConfig JMSDeliveryMode="PERSISTENT"/><con:jmsPropertyConfig/><con:parameters><entry key="naziv" value="Tekuci" xmlns="http://eviware.com/soapui/config"/></con:parameters><con:parameterOrder><con:entry>naziv</con:entry></con:parameterOrder></con:request></con:method></con:resource><con:resource name="Tip Racuna Insert" path="/tipRacuna" id="e777e981-18ad-4a76-9998-0da6ce54615c"><con:settings/><con:parameters/><con:method name="Method Insert" id="37008de6-4c59-4606-9a12-1a3bfd9dec25" method="POST"><con:settings/><con:parameters/><con:representation type="RESPONSE"><con:mediaType>application/json</con:mediaType><con:status>200</con:status><con:params/><con:element>Response</con:element></con:representation><con:representation type="FAULT"><con:mediaType>application/json</con:mediaType><con:status>500</con:status><con:params/><con:element xmlns:kred="http://localhost/kredit">kred:Fault</con:element></con:representation><con:representation type="REQUEST"><con:mediaType>application/json</con:mediaType><con:params/></con:representation><con:representation type="RESPONSE"><con:mediaType xsi:nil="true"/><con:status>200</con:status><con:params/><con:element>data</con:element></con:representation><con:representation type="RESPONSE"><con:mediaType xsi:nil="true"/><con:status>200</con:status><con:params/><con:element>data</con:element></con:representation><con:representation type="FAULT"><con:mediaType xsi:nil="true"/><con:status>409</con:status><con:params/><con:element>data</con:element></con:representation><con:representation type="RESPONSE"><con:mediaType xsi:nil="true"/><con:status>200</con:status><con:params/><con:element>data</con:element></con:representation><con:representation type="RESPONSE"><con:mediaType xsi:nil="true"/><con:status>200</con:status><con:params/><con:element>data</con:element></con:representation><con:representation type="RESPONSE"><con:mediaType xsi:nil="true"/><con:status>200</con:status><con:params/><con:element>data</con:element></con:representation><con:representation type="RESPONSE"><con:mediaType xsi:nil="true"/><con:status>200</con:status><con:params/><con:element>data</con:element></con:representation><con:representation type="RESPONSE"><con:mediaType xsi:nil="true"/><con:status>200</con:status><con:params/><con:element>data</con:element></con:representation><con:request name="Tip Racuna Insert" id="55b5b7b4-ab41-4887-bc57-ca7d68b59919" mediaType="application/json" postQueryString="false"><con:settings><con:setting id="com.eviware.soapui.impl.wsdl.WsdlRequest@request-headers">&lt;xml-fragment/></con:setting></con:settings><con:endpoint>http://localhost:8084</con:endpoint><con:request>{
      "id": -100,
      "naziv": "Insert",
      "opis": "Insert",
      "oznaka": "211"
   }</con:request><con:originalUri>http://localhost/kredit</con:originalUri><con:credentials><con:authType>No Authorization</con:authType></con:credentials><con:jmsConfig JMSDeliveryMode="PERSISTENT"/><con:jmsPropertyConfig/><con:parameters/></con:request></con:method></con:resource><con:resource name="Tip Racuna Update" path="/tipRacuna" id="e777e981-18ad-4a76-9998-0da6ce54615c"><con:settings/><con:parameters/><con:method name="Method Update" id="37008de6-4c59-4606-9a12-1a3bfd9dec25" method="PUT"><con:settings/><con:parameters/><con:representation type="RESPONSE"><con:mediaType>application/json</con:mediaType><con:status>200</con:status><con:params/><con:element>Response</con:element></con:representation><con:representation type="FAULT"><con:mediaType>application/json</con:mediaType><con:status>500</con:status><con:params/><con:element xmlns:kred="http://localhost/kredit">kred:Fault</con:element></con:representation><con:representation type="REQUEST"><con:mediaType>application/json</con:mediaType><con:params/></con:representation><con:representation type="RESPONSE"><con:mediaType xsi:nil="true"/><con:status>200</con:status><con:params/><con:element>data</con:element></con:representation><con:representation type="RESPONSE"><con:mediaType xsi:nil="true"/><con:status>200</con:status><con:params/><con:element>data</con:element></con:representation><con:representation type="RESPONSE"><con:mediaType xsi:nil="true"/><con:status>200</con:status><con:params/><con:element>data</con:element></con:representation><con:representation type="RESPONSE"><con:mediaType xsi:nil="true"/><con:status>200</con:status><con:params/><con:element>data</con:element></con:representation><con:request name="Tip Racuna Update" id="55b5b7b4-ab41-4887-bc57-ca7d68b59919" mediaType="application/json" postQueryString="false"><con:settings><con:setting id="com.eviware.soapui.impl.wsdl.WsdlRequest@request-headers">&lt;xml-fragment/></con:setting></con:settings><con:endpoint>http://localhost:8084</con:endpoint><con:request>{
      "id": -100,
      "naziv": "Update",
      "opis": "Update",
      "oznaka": "211"
   }</con:request><con:originalUri>http://localhost/kredit</con:originalUri><con:credentials><con:authType>No Authorization</con:authType></con:credentials><con:jmsConfig JMSDeliveryMode="PERSISTENT"/><con:jmsPropertyConfig/><con:parameters/></con:request></con:method></con:resource><con:resource name="Tip Racuna Delete" path="/tipRacuna/{id}" id="e777e981-18ad-4a76-9998-0da6ce54615c"><con:settings/><con:parameters><con:parameter><con:name>id</con:name><con:value>-46</con:value><con:style>TEMPLATE</con:style><con:default>-46</con:default></con:parameter></con:parameters><con:method name="Method Delete" id="37008de6-4c59-4606-9a12-1a3bfd9dec25" method="DELETE"><con:settings/><con:parameters/><con:representation type="RESPONSE"><con:mediaType>application/json</con:mediaType><con:status>200</con:status><con:params/><con:element>Response</con:element></con:representation><con:representation type="FAULT"><con:mediaType>application/json</con:mediaType><con:status>500</con:status><con:params/><con:element xmlns:kred="http://localhost/kredit">kred:Fault</con:element></con:representation><con:representation type="REQUEST"><con:mediaType>application/json</con:mediaType><con:params/></con:representation><con:representation type="RESPONSE"><con:mediaType xsi:nil="true"/><con:status>200</con:status><con:params/><con:element>data</con:element></con:representation><con:representation type="RESPONSE"><con:mediaType xsi:nil="true"/><con:status>200</con:status><con:params/><con:element>data</con:element></con:representation><con:representation type="RESPONSE"><con:mediaType xsi:nil="true"/><con:status>200</con:status><con:params/><con:element>data</con:element></con:representation><con:representation type="RESPONSE"><con:mediaType xsi:nil="true"/><con:status>200</con:status><con:params/><con:element>data</con:element></con:representation><con:representation type="RESPONSE"><con:mediaType xsi:nil="true"/><con:status>200</con:status><con:params/><con:element>data</con:element></con:representation><con:request name="Tip Racuna Delete" id="55b5b7b4-ab41-4887-bc57-ca7d68b59919" mediaType="application/json" postQueryString="false"><con:settings><con:setting id="com.eviware.soapui.impl.wsdl.WsdlRequest@request-headers">&lt;xml-fragment/></con:setting></con:settings><con:endpoint>http://localhost:8084</con:endpoint><con:request/><con:originalUri>http://localhost/kredit</con:originalUri><con:credentials><con:authType>No Authorization</con:authType></con:credentials><con:jmsConfig JMSDeliveryMode="PERSISTENT"/><con:jmsPropertyConfig/><con:parameters><entry key="id" value="-46" xmlns="http://eviware.com/soapui/config"/></con:parameters><con:parameterOrder><con:entry>id</con:entry></con:parameterOrder></con:request></con:method></con:resource><con:resource name="Klijent Get All" path="/klijent" id="e777e981-18ad-4a76-9998-0da6ce54615c"><con:settings/><con:parameters/><con:method name="Get All" id="37008de6-4c59-4606-9a12-1a3bfd9dec25" method="GET"><con:settings/><con:parameters/><con:representation type="RESPONSE"><con:mediaType>application/json</con:mediaType><con:status>200</con:status><con:params/><con:element>Response</con:element></con:representation><con:representation type="RESPONSE"><con:mediaType xsi:nil="true"/><con:status>0</con:status><con:params/><con:element>data</con:element></con:representation><con:request name="Klijent Get All" id="55b5b7b4-ab41-4887-bc57-ca7d68b59919" mediaType="application/json"><con:settings><con:setting id="com.eviware.soapui.impl.wsdl.WsdlRequest@request-headers">&lt;xml-fragment/></con:setting></con:settings><con:endpoint>http://localhost:8084</con:endpoint><con:request/><con:originalUri>http://localhost/kredit</con:originalUri><con:credentials><con:authType>No Authorization</con:authType></con:credentials><con:jmsConfig JMSDeliveryMode="PERSISTENT"/><con:jmsPropertyConfig/><con:parameters/></con:request></con:method></con:resource><con:resource name="Klijent Get By ID" path="/klijent/{id}" id="b1902b8a-682d-4b88-a303-5da0b9e7edf1"><con:settings/><con:parameters><con:parameter><con:name>id</con:name><con:value>1</con:value><con:style>TEMPLATE</con:style><con:default>1</con:default></con:parameter></con:parameters><con:method name="Method Get By ID" id="ada7ab53-82bf-416f-8210-b48c9d6bb23d" method="GET"><con:settings/><con:parameters/><con:representation type="RESPONSE"><con:mediaType>application/json</con:mediaType><con:status>200</con:status><con:params/><con:element xmlns:ns="http://localhost/kredit/1">ns:Response</con:element></con:representation><con:request name="Klijent Get By ID" id="17313365-ee72-4b2a-bffd-1db42ec4582e" mediaType="application/json"><con:settings><con:setting id="com.eviware.soapui.impl.wsdl.WsdlRequest@request-headers">&lt;xml-fragment/></con:setting></con:settings><con:endpoint>http://localhost:8084</con:endpoint><con:request/><con:originalUri>http://localhost/kredit/1</con:originalUri><con:credentials><con:authType>No Authorization</con:authType></con:credentials><con:jmsConfig JMSDeliveryMode="PERSISTENT"/><con:jmsPropertyConfig/><con:parameters><entry key="id" value="1" xmlns="http://eviware.com/soapui/config"/></con:parameters><con:parameterOrder><con:entry>id</con:entry></con:parameterOrder></con:request></con:method></con:resource><con:resource name="Klijent Get By Kredit" path="/klijentPoKreditu/{id}" id="b1902b8a-682d-4b88-a303-5da0b9e7edf1"><con:settings/><con:parameters><con:parameter><con:name>id</con:name><con:value>1</con:value><con:style>TEMPLATE</con:style><con:default>1</con:default></con:parameter></con:parameters><con:method name="Method Get By Kredit" id="ada7ab53-82bf-416f-8210-b48c9d6bb23d" method="GET"><con:settings/><con:parameters/><con:representation type="RESPONSE"><con:mediaType>application/json</con:mediaType><con:status>200</con:status><con:params/><con:element xmlns:ns="http://localhost/kredit/1">ns:Response</con:element></con:representation><con:request name="Klijent Get By Kredit" id="17313365-ee72-4b2a-bffd-1db42ec4582e" mediaType="application/json"><con:settings><con:setting id="com.eviware.soapui.impl.wsdl.WsdlRequest@request-headers">&lt;xml-fragment/></con:setting></con:settings><con:endpoint>http://localhost:8084</con:endpoint><con:request/><con:originalUri>http://localhost/kredit/1</con:originalUri><con:credentials><con:authType>No Authorization</con:authType></con:credentials><con:jmsConfig JMSDeliveryMode="PERSISTENT"/><con:jmsPropertyConfig/><con:parameters><entry key="id" value="1" xmlns="http://eviware.com/soapui/config"/></con:parameters><con:parameterOrder><con:entry>id</con:entry></con:parameterOrder></con:request></con:method></con:resource><con:resource name="Klijent Insert" path="/klijent" id="e777e981-18ad-4a76-9998-0da6ce54615c"><con:settings/><con:parameters/><con:method name="Method Insert" id="37008de6-4c59-4606-9a12-1a3bfd9dec25" method="POST"><con:settings/><con:parameters/><con:representation type="RESPONSE"><con:mediaType>application/json</con:mediaType><con:status>200</con:status><con:params/><con:element>Response</con:element></con:representation><con:representation type="FAULT"><con:mediaType>application/json</con:mediaType><con:status>500</con:status><con:params/><con:element xmlns:kred="http://localhost/kredit">kred:Fault</con:element></con:representation><con:representation type="REQUEST"><con:mediaType>application/json</con:mediaType><con:params/></con:representation><con:representation type="RESPONSE"><con:mediaType xsi:nil="true"/><con:status>200</con:status><con:params/><con:element>data</con:element></con:representation><con:representation type="RESPONSE"><con:mediaType xsi:nil="true"/><con:status>200</con:status><con:params/><con:element>data</con:element></con:representation><con:representation type="RESPONSE"><con:mediaType xsi:nil="true"/><con:status>200</con:status><con:params/><con:element>data</con:element></con:representation><con:representation type="RESPONSE"><con:mediaType xsi:nil="true"/><con:status>200</con:status><con:params/><con:element>data</con:element></con:representation><con:representation type="RESPONSE"><con:mediaType xsi:nil="true"/><con:status>200</con:status><con:params/><con:element>data</con:element></con:representation><con:representation type="RESPONSE"><con:mediaType xsi:nil="true"/><con:status>200</con:status><con:params/><con:element>data</con:element></con:representation><con:representation type="RESPONSE"><con:mediaType xsi:nil="true"/><con:status>200</con:status><con:params/><con:element>data</con:element></con:representation><con:representation type="RESPONSE"><con:mediaType xsi:nil="true"/><con:status>200</con:status><con:params/><con:element>data</con:element></con:representation><con:representation type="RESPONSE"><con:mediaType xsi:nil="true"/><con:status>200</con:status><con:params/><con:element>data</con:element></con:representation><con:request name="Klijent Insert" id="55b5b7b4-ab41-4887-bc57-ca7d68b59919" mediaType="application/json" postQueryString="false"><con:settings><con:setting id="com.eviware.soapui.impl.wsdl.WsdlRequest@request-headers">&lt;xml-fragment/></con:setting></con:settings><con:endpoint>http://localhost:8084</con:endpoint><con:request>{
   "id": -45,
   "brojLk": 285937204,
   "ime": "Insert",
   "prezime": "Insert",
   "kredit":    {
      "id": 2,
      "naziv": "Stambeni",
      "opis": "Stambeni kredit je namenjen kupovini nekog stambenog objekta i formalno klijent postaje njegov vlasnik ali i u principu na taj stan se stavlja hipoteka u korist banke koja je odobrila kredit.",
      "oznaka": "2"
   }
}</con:request><con:originalUri>http://localhost/kredit</con:originalUri><con:credentials><con:authType>No Authorization</con:authType></con:credentials><con:jmsConfig JMSDeliveryMode="PERSISTENT"/><con:jmsPropertyConfig/><con:parameters/></con:request></con:method></con:resource><con:resource name="Klijent Update" path="/klijent" id="e777e981-18ad-4a76-9998-0da6ce54615c"><con:settings/><con:parameters/><con:method name="Method Update" id="37008de6-4c59-4606-9a12-1a3bfd9dec25" method="PUT"><con:settings/><con:parameters/><con:representation type="RESPONSE"><con:mediaType>application/json</con:mediaType><con:status>200</con:status><con:params/><con:element>Response</con:element></con:representation><con:representation type="FAULT"><con:mediaType>application/json</con:mediaType><con:status>500</con:status><con:params/><con:element xmlns:kred="http://localhost/kredit">kred:Fault</con:element></con:representation><con:representation type="REQUEST"><con:mediaType>application/json</con:mediaType><con:params/></con:representation><con:representation type="RESPONSE"><con:mediaType xsi:nil="true"/><con:status>200</con:status><con:params/><con:element>data</con:element></con:representation><con:representation type="RESPONSE"><con:mediaType xsi:nil="true"/><con:status>200</con:status><con:params/><con:element>data</con:element></con:representation><con:representation type="RESPONSE"><con:mediaType xsi:nil="true"/><con:status>200</con:status><con:params/><con:element>data</con:element></con:representation><con:request name="Klijent Update" id="55b5b7b4-ab41-4887-bc57-ca7d68b59919" mediaType="application/json" postQueryString="false"><con:settings><con:setting id="com.eviware.soapui.impl.wsdl.WsdlRequest@request-headers">&lt;xml-fragment/></con:setting></con:settings><con:endpoint>http://localhost:8084</con:endpoint><con:request>{
   "id": -100,
   "brojLk": 285937204,
   "ime": "Update",
   "prezime": "Update",
   "kredit":    {
      "id": 2,
      "naziv": "Stambeni",
      "opis": "Stambeni kredit je namenjen kupovini nekog stambenog objekta i formalno klijent postaje njegov vlasnik ali i u principu na taj stan se stavlja hipoteka u korist banke koja je odobrila kredit.",
      "oznaka": "2"
   }
}</con:request><con:originalUri>http://localhost/kredit</con:originalUri><con:credentials><con:authType>No Authorization</con:authType></con:credentials><con:jmsConfig JMSDeliveryMode="PERSISTENT"/><con:jmsPropertyConfig/><con:parameters/></con:request></con:method></con:resource><con:resource name="Klijent Delete" path="/klijent/{id}" id="e777e981-18ad-4a76-9998-0da6ce54615c"><con:settings/><con:parameters><con:parameter><con:name>id</con:name><con:value>-100</con:value><con:style>TEMPLATE</con:style><con:default>-100</con:default></con:parameter></con:parameters><con:method name="Method Delete" id="37008de6-4c59-4606-9a12-1a3bfd9dec25" method="DELETE"><con:settings/><con:parameters/><con:representation type="RESPONSE"><con:mediaType>application/json</con:mediaType><con:status>200</con:status><con:params/><con:element>Response</con:element></con:representation><con:representation type="FAULT"><con:mediaType>application/json</con:mediaType><con:status>500</con:status><con:params/><con:element xmlns:kred="http://localhost/kredit">kred:Fault</con:element></con:representation><con:representation type="REQUEST"><con:mediaType>application/json</con:mediaType><con:params/></con:representation><con:representation type="RESPONSE"><con:mediaType xsi:nil="true"/><con:status>200</con:status><con:params/><con:element>data</con:element></con:representation><con:representation type="RESPONSE"><con:mediaType xsi:nil="true"/><con:status>200</con:status><con:params/><con:element>data</con:element></con:representation><con:representation type="RESPONSE"><con:mediaType xsi:nil="true"/><con:status>200</con:status><con:params/><con:element>data</con:element></con:representation><con:representation type="RESPONSE"><con:mediaType xsi:nil="true"/><con:status>204</con:status><con:params/><con:element>data</con:element></con:representation><con:representation type="RESPONSE"><con:mediaType xsi:nil="true"/><con:status>200</con:status><con:params/><con:element>data</con:element></con:representation><con:representation type="RESPONSE"><con:mediaType xsi:nil="true"/><con:status>204</con:status><con:params/><con:element>data</con:element></con:representation><con:representation type="RESPONSE"><con:mediaType xsi:nil="true"/><con:status>200</con:status><con:params/><con:element>data</con:element></con:representation><con:representation type="RESPONSE"><con:mediaType xsi:nil="true"/><con:status>0</con:status><con:params/><con:element>data</con:element></con:representation><con:representation type="RESPONSE"><con:mediaType xsi:nil="true"/><con:status>200</con:status><con:params/><con:element>data</con:element></con:representation><con:request name="Klijent Delete" id="55b5b7b4-ab41-4887-bc57-ca7d68b59919" mediaType="application/json" postQueryString="false"><con:settings><con:setting id="com.eviware.soapui.impl.wsdl.WsdlRequest@request-headers">&lt;xml-fragment/></con:setting></con:settings><con:endpoint>http://localhost:8084</con:endpoint><con:request/><con:originalUri>http://localhost/kredit</con:originalUri><con:credentials><con:authType>No Authorization</con:authType></con:credentials><con:jmsConfig JMSDeliveryMode="PERSISTENT"/><con:jmsPropertyConfig/><con:parameters/><con:parameterOrder><con:entry>id</con:entry></con:parameterOrder></con:request></con:method></con:resource><con:resource name="Racun Get By Tip Racuna" path="/racunPoTipuRacuna/{id}" id="b1902b8a-682d-4b88-a303-5da0b9e7edf1"><con:settings/><con:parameters><con:parameter><con:name>id</con:name><con:value>1</con:value><con:style>TEMPLATE</con:style><con:default>1</con:default></con:parameter></con:parameters><con:method name="Method Get By Tip Racuna" id="ada7ab53-82bf-416f-8210-b48c9d6bb23d" method="GET"><con:settings/><con:parameters/><con:representation type="RESPONSE"><con:mediaType>application/json</con:mediaType><con:status>200</con:status><con:params/><con:element xmlns:ns="http://localhost/kredit/1">ns:Response</con:element></con:representation><con:request name="Racun Get By Tip Racuna" id="17313365-ee72-4b2a-bffd-1db42ec4582e" mediaType="application/json"><con:settings><con:setting id="com.eviware.soapui.impl.wsdl.WsdlRequest@request-headers">&lt;xml-fragment/></con:setting></con:settings><con:endpoint>http://localhost:8084</con:endpoint><con:request/><con:originalUri>http://localhost/kredit/1</con:originalUri><con:credentials><con:authType>No Authorization</con:authType></con:credentials><con:jmsConfig JMSDeliveryMode="PERSISTENT"/><con:jmsPropertyConfig/><con:parameters><entry key="id" value="1" xmlns="http://eviware.com/soapui/config"/></con:parameters><con:parameterOrder><con:entry>id</con:entry></con:parameterOrder></con:request></con:method></con:resource><con:resource name="Racun Get By Klijent" path="/racunPoKlijentu/{id}" id="b1902b8a-682d-4b88-a303-5da0b9e7edf1"><con:settings/><con:parameters><con:parameter><con:name>id</con:name><con:value>1</con:value><con:style>TEMPLATE</con:style><con:default>1</con:default></con:parameter></con:parameters><con:method name="Method Get By Klijent" id="ada7ab53-82bf-416f-8210-b48c9d6bb23d" method="GET"><con:settings/><con:parameters/><con:representation type="RESPONSE"><con:mediaType>application/json</con:mediaType><con:status>200</con:status><con:params/><con:element xmlns:ns="http://localhost/kredit/1">ns:Response</con:element></con:representation><con:request name="Racun Get By Klijent" id="17313365-ee72-4b2a-bffd-1db42ec4582e" mediaType="application/json"><con:settings><con:setting id="com.eviware.soapui.impl.wsdl.WsdlRequest@request-headers">&lt;xml-fragment/></con:setting></con:settings><con:endpoint>http://localhost:8084</con:endpoint><con:request/><con:originalUri>http://localhost/kredit/1</con:originalUri><con:credentials><con:authType>No Authorization</con:authType></con:credentials><con:jmsConfig JMSDeliveryMode="PERSISTENT"/><con:jmsPropertyConfig/><con:parameters><entry key="id" value="1" xmlns="http://eviware.com/soapui/config"/></con:parameters><con:parameterOrder><con:entry>id</con:entry></con:parameterOrder></con:request></con:method></con:resource><con:resource name="Racun Get All" path="/racun" id="e777e981-18ad-4a76-9998-0da6ce54615c"><con:settings/><con:parameters/><con:method name="Get All" id="37008de6-4c59-4606-9a12-1a3bfd9dec25" method="GET"><con:settings/><con:parameters/><con:representation type="RESPONSE"><con:mediaType>application/json</con:mediaType><con:status>200</con:status><con:params/><con:element>Response</con:element></con:representation><con:representation type="RESPONSE"><con:mediaType xsi:nil="true"/><con:status>0</con:status><con:params/><con:element>data</con:element></con:representation><con:request name="Racun Get All" id="55b5b7b4-ab41-4887-bc57-ca7d68b59919" mediaType="application/json"><con:settings><con:setting id="com.eviware.soapui.impl.wsdl.WsdlRequest@request-headers">&lt;xml-fragment/></con:setting></con:settings><con:endpoint>http://localhost:8084</con:endpoint><con:request/><con:originalUri>http://localhost/kredit</con:originalUri><con:credentials><con:authType>No Authorization</con:authType></con:credentials><con:jmsConfig JMSDeliveryMode="PERSISTENT"/><con:jmsPropertyConfig/><con:parameters/></con:request></con:method></con:resource><con:resource name="Racun Get By ID" path="/racun/{id}" id="b1902b8a-682d-4b88-a303-5da0b9e7edf1"><con:settings/><con:parameters><con:parameter><con:name>id</con:name><con:value>1</con:value><con:style>TEMPLATE</con:style><con:default>1</con:default></con:parameter></con:parameters><con:method name="Method Get By ID" id="ada7ab53-82bf-416f-8210-b48c9d6bb23d" method="GET"><con:settings/><con:parameters/><con:representation type="RESPONSE"><con:mediaType>application/json</con:mediaType><con:status>200</con:status><con:params/><con:element xmlns:ns="http://localhost/kredit/1">ns:Response</con:element></con:representation><con:request name="Racun Get By ID" id="17313365-ee72-4b2a-bffd-1db42ec4582e" mediaType="application/json"><con:settings><con:setting id="com.eviware.soapui.impl.wsdl.WsdlRequest@request-headers">&lt;xml-fragment/></con:setting></con:settings><con:endpoint>http://localhost:8084</con:endpoint><con:request/><con:originalUri>http://localhost/kredit/1</con:originalUri><con:credentials><con:authType>No Authorization</con:authType></con:credentials><con:jmsConfig JMSDeliveryMode="PERSISTENT"/><con:jmsPropertyConfig/><con:parameters><entry key="id" value="1" xmlns="http://eviware.com/soapui/config"/></con:parameters><con:parameterOrder><con:entry>id</con:entry></con:parameterOrder></con:request></con:method></con:resource><con:resource name="Racun Insert" path="/racun" id="e777e981-18ad-4a76-9998-0da6ce54615c"><con:settings/><con:parameters/><con:method name="Method Insert" id="37008de6-4c59-4606-9a12-1a3bfd9dec25" method="POST"><con:settings/><con:parameters/><con:representation type="RESPONSE"><con:mediaType>application/json</con:mediaType><con:status>200</con:status><con:params/><con:element>Response</con:element></con:representation><con:representation type="FAULT"><con:mediaType>application/json</con:mediaType><con:status>500</con:status><con:params/><con:element xmlns:kred="http://localhost/kredit">kred:Fault</con:element></con:representation><con:representation type="REQUEST"><con:mediaType>application/json</con:mediaType><con:params/></con:representation><con:representation type="RESPONSE"><con:mediaType xsi:nil="true"/><con:status>200</con:status><con:params/><con:element>data</con:element></con:representation><con:representation type="RESPONSE"><con:mediaType xsi:nil="true"/><con:status>200</con:status><con:params/><con:element>data</con:element></con:representation><con:representation type="RESPONSE"><con:mediaType xsi:nil="true"/><con:status>200</con:status><con:params/><con:element>data</con:element></con:representation><con:representation type="RESPONSE"><con:mediaType xsi:nil="true"/><con:status>200</con:status><con:params/><con:element>data</con:element></con:representation><con:representation type="RESPONSE"><con:mediaType xsi:nil="true"/><con:status>200</con:status><con:params/><con:element>data</con:element></con:representation><con:representation type="RESPONSE"><con:mediaType xsi:nil="true"/><con:status>200</con:status><con:params/><con:element>data</con:element></con:representation><con:representation type="RESPONSE"><con:mediaType xsi:nil="true"/><con:status>200</con:status><con:params/><con:element>data</con:element></con:representation><con:representation type="RESPONSE"><con:mediaType xsi:nil="true"/><con:status>200</con:status><con:params/><con:element>data</con:element></con:representation><con:request name="Racun Insert" id="55b5b7b4-ab41-4887-bc57-ca7d68b59919" mediaType="application/json" postQueryString="false"><con:settings><con:setting id="com.eviware.soapui.impl.wsdl.WsdlRequest@request-headers">&lt;xml-fragment/></con:setting></con:settings><con:endpoint>http://localhost:8084</con:endpoint><con:request>{
   "id": -45,
   "naziv": "Insert",
   "opis": "Insert",
   "oznaka": "1",
   "klijent":    {
      "id": 4,
      "brojLk": 985648276,
      "ime": "Luka",
      "prezime": "Lukic",
      "kredit":       {
         "id": 3,
         "naziv": "Studentski",
         "opis": "Studentski kredit je namenjen samo i iskljucivo studentima i koristi se za finansiranje studija ili studentskih potreba poput placanja smestaja i hrane u studentskim domovima",
         "oznaka": "3"
      }
   },
   "tipRacuna":    {
      "id": 1,
      "naziv": "Tekuci",
      "opis": "Racun na temelju kojega se mogu uzimati cekovi i dogovoriti PREKORACENJE. Tekuci racuni obicno ne nose znatnije iznose KAMATA na pozitivna salda",
      "oznaka": "1"
   }
}</con:request><con:originalUri>http://localhost/kredit</con:originalUri><con:credentials><con:authType>No Authorization</con:authType></con:credentials><con:jmsConfig JMSDeliveryMode="PERSISTENT"/><con:jmsPropertyConfig/><con:parameters/></con:request></con:method></con:resource><con:resource name="Racun Update" path="/racun" id="e777e981-18ad-4a76-9998-0da6ce54615c"><con:settings/><con:parameters/><con:method name="Method Update" id="37008de6-4c59-4606-9a12-1a3bfd9dec25" method="PUT"><con:settings/><con:parameters/><con:representation type="RESPONSE"><con:mediaType>application/json</con:mediaType><con:status>200</con:status><con:params/><con:element>Response</con:element></con:representation><con:representation type="FAULT"><con:mediaType>application/json</con:mediaType><con:status>500</con:status><con:params/><con:element xmlns:kred="http://localhost/kredit">kred:Fault</con:element></con:representation><con:representation type="REQUEST"><con:mediaType>application/json</con:mediaType><con:params/></con:representation><con:representation type="RESPONSE"><con:mediaType xsi:nil="true"/><con:status>200</con:status><con:params/><con:element>data</con:element></con:representation><con:representation type="RESPONSE"><con:mediaType xsi:nil="true"/><con:status>200</con:status><con:params/><con:element>data</con:element></con:representation><con:representation type="RESPONSE"><con:mediaType xsi:nil="true"/><con:status>200</con:status><con:params/><con:element>data</con:element></con:representation><con:representation type="RESPONSE"><con:mediaType xsi:nil="true"/><con:status>200</con:status><con:params/><con:element>data</con:element></con:representation><con:representation type="RESPONSE"><con:mediaType xsi:nil="true"/><con:status>200</con:status><con:params/><con:element>data</con:element></con:representation><con:representation type="RESPONSE"><con:mediaType xsi:nil="true"/><con:status>200</con:status><con:params/><con:element>data</con:element></con:representation><con:request name="Racun Update" id="55b5b7b4-ab41-4887-bc57-ca7d68b59919" mediaType="application/json" postQueryString="false"><con:settings><con:setting id="com.eviware.soapui.impl.wsdl.WsdlRequest@request-headers">&lt;xml-fragment/></con:setting></con:settings><con:endpoint>http://localhost:8084</con:endpoint><con:request>{
   "id": -100,
   "naziv": "update",
   "opis": "update",
   "oznaka": "1",
   "klijent":    {
      "id": 4,
      "brojLk": 985648276,
      "ime": "Luka",
      "prezime": "Lukic",
      "kredit":       {
         "id": 3,
         "naziv": "Studentski",
         "opis": "Studentski kredit je namenjen samo i iskljucivo studentima i koristi se za finansiranje studija ili studentskih potreba poput placanja smestaja i hrane u studentskim domovima",
         "oznaka": "3"
      }
   },
   "tipRacuna":    {
      "id": 1,
      "naziv": "Tekuci",
      "opis": "Racun na temelju kojega se mogu uzimati cekovi i dogovoriti PREKORACENJE. Tekuci racuni obicno ne nose znatnije iznose KAMATA na pozitivna salda",
      "oznaka": "1"
   }
}</con:request><con:originalUri>http://localhost/kredit</con:originalUri><con:credentials><con:authType>No Authorization</con:authType></con:credentials><con:jmsConfig JMSDeliveryMode="PERSISTENT"/><con:jmsPropertyConfig/><con:parameters/><con:parameterOrder/></con:request></con:method></con:resource><con:resource name="Racun Delete" path="/kredit/{id}" id="e777e981-18ad-4a76-9998-0da6ce54615c"><con:settings/><con:parameters><con:parameter><con:name>id</con:name><con:value>-100</con:value><con:style>TEMPLATE</con:style><con:default>-100</con:default></con:parameter></con:parameters><con:method name="Method Delete" id="37008de6-4c59-4606-9a12-1a3bfd9dec25" method="DELETE"><con:settings/><con:parameters/><con:representation type="RESPONSE"><con:mediaType>application/json</con:mediaType><con:status>200</con:status><con:params/><con:element>Response</con:element></con:representation><con:representation type="FAULT"><con:mediaType>application/json</con:mediaType><con:status>500</con:status><con:params/><con:element xmlns:kred="http://localhost/kredit">kred:Fault</con:element></con:representation><con:representation type="REQUEST"><con:mediaType>application/json</con:mediaType><con:params/></con:representation><con:representation type="RESPONSE"><con:mediaType xsi:nil="true"/><con:status>200</con:status><con:params/><con:element>data</con:element></con:representation><con:representation type="RESPONSE"><con:mediaType xsi:nil="true"/><con:status>200</con:status><con:params/><con:element>data</con:element></con:representation><con:representation type="RESPONSE"><con:mediaType xsi:nil="true"/><con:status>200</con:status><con:params/><con:element>data</con:element></con:representation><con:request name="Racun Delete" id="55b5b7b4-ab41-4887-bc57-ca7d68b59919" mediaType="application/json" postQueryString="false"><con:settings><con:setting id="com.eviware.soapui.impl.wsdl.WsdlRequest@request-headers">&lt;xml-fragment/></con:setting></con:settings><con:endpoint>http://localhost:8084</con:endpoint><con:request/><con:originalUri>http://localhost/kredit</con:originalUri><con:credentials><con:authType>No Authorization</con:authType></con:credentials><con:jmsConfig JMSDeliveryMode="PERSISTENT"/><con:jmsPropertyConfig/><con:parameters><entry key="id" value="-100" xmlns="http://eviware.com/soapui/config"/></con:parameters><con:parameterOrder><con:entry>id</con:entry></con:parameterOrder></con:request></con:method></con:resource></con:interface><con:testSuite id="1db450c2-612e-475b-bac1-44737909a67a" name="http://localhost:8084 TestSuite"><con:description>TestSuite generated for REST Service [http://localhost:8084]</con:description><con:settings/><con:runType>SEQUENTIAL</con:runType><con:testCase id="31e6d942-cf07-4fb6-a83b-9bc2b3036493" failOnError="true" failTestCaseOnErrors="true" keepSession="false" maxResults="0" name="http://localhost:8084 TestSuite" searchProperties="true"><con:settings/><con:testStep type="restrequest" name="Kredit Get All" id="f148adda-862c-4b13-9a6b-56a01b46fea2"><con:settings/><con:config service="http://localhost:8084" resourcePath="/kredit" methodName="Get All" xsi:type="con:RestRequestStep" xmlns:xsi="http://www.w3.org/2001/XMLSchema-instance"><con:restRequest name="Kredit Get All" id="55b5b7b4-ab41-4887-bc57-ca7d68b59919" mediaType="application/json"><con:settings><con:setting id="com.eviware.soapui.impl.wsdl.WsdlRequest@request-headers">&lt;xml-fragment/></con:setting></con:settings><con:endpoint>http://localhost:8084</con:endpoint><con:request/><con:originalUri>http://localhost/kredit</con:originalUri><con:assertion type="Valid HTTP Status Codes" id="9ecdc694-164b-44a0-a4fd-507edb5ac6c8" name="Valid HTTP Status Codes"><con:configuration><codes>200</codes></con:configuration></con:assertion><con:credentials><con:authType>No Authorization</con:authType></con:credentials><con:jmsConfig JMSDeliveryMode="PERSISTENT"/><con:jmsPropertyConfig/><con:parameters/></con:restRequest></con:config></con:testStep><con:testStep type="restrequest" name="Kredit Get By ID" id="efdaac3e-33cd-4478-b660-4f96ea3fb075"><con:settings/><con:config service="http://localhost:8084" resourcePath="/kredit/{id}" methodName="Method Get By ID" xsi:type="con:RestRequestStep" xmlns:xsi="http://www.w3.org/2001/XMLSchema-instance"><con:restRequest name="Kredit Get By ID" id="17313365-ee72-4b2a-bffd-1db42ec4582e" mediaType="application/json"><con:settings><con:setting id="com.eviware.soapui.impl.wsdl.WsdlRequest@request-headers">&lt;xml-fragment/></con:setting></con:settings><con:endpoint>http://localhost:8084</con:endpoint><con:request/><con:originalUri>http://localhost/kredit/1</con:originalUri><con:assertion type="Valid HTTP Status Codes" id="65c8c7f1-cc90-4498-b6b3-0c61cc679a9f" name="Valid HTTP Status Codes"><con:configuration><codes>200</codes></con:configuration></con:assertion><con:credentials><con:authType>No Authorization</con:authType></con:credentials><con:jmsConfig JMSDeliveryMode="PERSISTENT"/><con:jmsPropertyConfig/><con:parameters><entry key="id" value="1" xmlns="http://eviware.com/soapui/config"/></con:parameters><con:parameterOrder><con:entry>id</con:entry></con:parameterOrder></con:restRequest></con:config></con:testStep><con:testStep type="restrequest" name="Kredit Get By Naziv" id="04330ea3-4e71-444d-a441-42d2c5a8ecae"><con:settings/><con:config service="http://localhost:8084" resourcePath="/kreditNaziv/{naziv}" methodName="Method Get By Naziv" xsi:type="con:RestRequestStep" xmlns:xsi="http://www.w3.org/2001/XMLSchema-instance"><con:restRequest name="Kredit Get By Naziv" id="17313365-ee72-4b2a-bffd-1db42ec4582e" mediaType="application/json"><con:settings><con:setting id="com.eviware.soapui.impl.wsdl.WsdlRequest@request-headers">&lt;xml-fragment/></con:setting></con:settings><con:endpoint>http://localhost:8084</con:endpoint><con:request/><con:originalUri>http://localhost/kredit/1</con:originalUri><con:assertion type="Valid HTTP Status Codes" id="4b1c8450-a106-4ff9-8859-afa175942bb6" name="Valid HTTP Status Codes"><con:configuration><codes>200</codes></con:configuration></con:assertion><con:credentials><con:authType>No Authorization</con:authType></con:credentials><con:jmsConfig JMSDeliveryMode="PERSISTENT"/><con:jmsPropertyConfig/><con:parameters>
  <con:entry key="naziv" value="Stambeni"/>
  <con:entry key="id" value="1"/>
</con:parameters><con:parameterOrder><con:entry>id</con:entry><con:entry>naziv</con:entry></con:parameterOrder></con:restRequest></con:config></con:testStep><con:testStep type="restrequest" name="Kredit Insert" id="93c9985b-8f82-49fc-ac7d-405f7afcc32e"><con:settings/><con:config service="http://localhost:8084" resourcePath="/kredit" methodName="Method Insert" xsi:type="con:RestRequestStep" xmlns:xsi="http://www.w3.org/2001/XMLSchema-instance"><con:restRequest name="Kredit Insert" id="55b5b7b4-ab41-4887-bc57-ca7d68b59919" mediaType="application/json" postQueryString="false"><con:settings><con:setting id="com.eviware.soapui.impl.wsdl.WsdlRequest@request-headers">&lt;xml-fragment/></con:setting></con:settings><con:endpoint>http://localhost:8084</con:endpoint><con:request>{
      "id": -46,
      "naziv": "Insert Kredit",
      "opis": "Insert Kredit",
      "oznaka": "123"
   }</con:request><con:originalUri>http://localhost/kredit</con:originalUri><con:assertion type="Valid HTTP Status Codes" id="8c304b5c-b698-40ac-b423-f484913c458e" name="Valid HTTP Status Codes"><con:configuration><codes>200</codes></con:configuration></con:assertion><con:credentials><con:authType>No Authorization</con:authType></con:credentials><con:jmsConfig JMSDeliveryMode="PERSISTENT"/><con:jmsPropertyConfig/><con:parameters/></con:restRequest></con:config></con:testStep><con:testStep type="restrequest" name="Kredit Update" id="afab0378-1d5e-4e6f-8990-efe2b00ff51d"><con:settings/><con:config service="http://localhost:8084" resourcePath="/kredit" methodName="Method Update" xsi:type="con:RestRequestStep" xmlns:xsi="http://www.w3.org/2001/XMLSchema-instance"><con:restRequest name="Kredit Update" id="55b5b7b4-ab41-4887-bc57-ca7d68b59919" mediaType="application/json" postQueryString="false"><con:settings><con:setting id="com.eviware.soapui.impl.wsdl.WsdlRequest@request-headers">&lt;xml-fragment/></con:setting></con:settings><con:endpoint>http://localhost:8084</con:endpoint><con:request> {
      "id": -100,
      "naziv": "Update Kredit",
      "opis": "Update Kredit",
      "oznaka": "123"
   }</con:request><con:originalUri>http://localhost/kredit</con:originalUri><con:assertion type="Valid HTTP Status Codes" id="b45e0f31-f7c3-46d2-b2ab-89391fdc9e76" name="Valid HTTP Status Codes"><con:configuration><codes>200</codes></con:configuration></con:assertion><con:credentials><con:authType>No Authorization</con:authType></con:credentials><con:jmsConfig JMSDeliveryMode="PERSISTENT"/><con:jmsPropertyConfig/><con:parameters/><con:parameterOrder/></con:restRequest></con:config></con:testStep><con:testStep type="restrequest" name="Kredit Delete" id="1cbfa26d-eed4-43c4-830b-e654e423c3c8"><con:settings/><con:config service="http://localhost:8084" resourcePath="/kredit/{id}" methodName="Method Delete" xsi:type="con:RestRequestStep" xmlns:xsi="http://www.w3.org/2001/XMLSchema-instance"><con:restRequest name="Kredit Delete" id="55b5b7b4-ab41-4887-bc57-ca7d68b59919" mediaType="application/json" postQueryString="false"><con:settings><con:setting id="com.eviware.soapui.impl.wsdl.WsdlRequest@request-headers">&lt;xml-fragment/></con:setting></con:settings><con:endpoint>http://localhost:8084</con:endpoint><con:request/><con:originalUri>http://localhost/kredit</con:originalUri><con:assertion type="Valid HTTP Status Codes" id="cebabbec-e15f-4017-852d-af419b7fc023" name="Valid HTTP Status Codes"><con:configuration><codes>200</codes></con:configuration></con:assertion><con:credentials><con:authType>No Authorization</con:authType></con:credentials><con:jmsConfig JMSDeliveryMode="PERSISTENT"/><con:jmsPropertyConfig/><con:parameters><entry key="id" value="-100" xmlns="http://eviware.com/soapui/config"/></con:parameters><con:parameterOrder><con:entry>id</con:entry></con:parameterOrder></con:restRequest></con:config></con:testStep><con:testStep type="restrequest" name="Tip Racuna Get All" id="e9edca3b-739f-4b3f-9eb2-a4347ffb055a"><con:settings/><con:config service="http://localhost:8084" resourcePath="/tipRacuna" methodName="Get All" xsi:type="con:RestRequestStep" xmlns:xsi="http://www.w3.org/2001/XMLSchema-instance"><con:restRequest name="Tip Racuna Get All" id="55b5b7b4-ab41-4887-bc57-ca7d68b59919" mediaType="application/json"><con:settings><con:setting id="com.eviware.soapui.impl.wsdl.WsdlRequest@request-headers">&lt;xml-fragment/></con:setting></con:settings><con:endpoint>http://localhost:8084</con:endpoint><con:request/><con:originalUri>http://localhost/kredit</con:originalUri><con:assertion type="Valid HTTP Status Codes" id="486814da-1d20-43ed-b9e3-cca1effbcc6b" name="Valid HTTP Status Codes"><con:configuration><codes>200</codes></con:configuration></con:assertion><con:credentials><con:authType>No Authorization</con:authType></con:credentials><con:jmsConfig JMSDeliveryMode="PERSISTENT"/><con:jmsPropertyConfig/><con:parameters/></con:restRequest></con:config></con:testStep><con:testStep type="restrequest" name="Tip Racuna Get By ID" id="ddd961fa-5293-4fef-8992-2f8254119fec"><con:settings/><con:config service="http://localhost:8084" resourcePath="/tipRacuna/{id}" methodName="Method Get By ID" xsi:type="con:RestRequestStep" xmlns:xsi="http://www.w3.org/2001/XMLSchema-instance"><con:restRequest name="Tip Racuna Get By ID" id="17313365-ee72-4b2a-bffd-1db42ec4582e" mediaType="application/json"><con:settings><con:setting id="com.eviware.soapui.impl.wsdl.WsdlRequest@request-headers">&lt;xml-fragment/></con:setting></con:settings><con:endpoint>http://localhost:8084</con:endpoint><con:request/><con:originalUri>http://localhost/kredit/1</con:originalUri><con:assertion type="Valid HTTP Status Codes" id="61a2c780-efdb-4c4d-a5a9-4f6f0e0a4151" name="Valid HTTP Status Codes"><con:configuration><codes>200</codes></con:configuration></con:assertion><con:credentials><con:authType>No Authorization</con:authType></con:credentials><con:jmsConfig JMSDeliveryMode="PERSISTENT"/><con:jmsPropertyConfig/><con:parameters><entry key="id" value="1" xmlns="http://eviware.com/soapui/config"/></con:parameters><con:parameterOrder><con:entry>id</con:entry></con:parameterOrder></con:restRequest></con:config></con:testStep><con:testStep type="restrequest" name="Tip Racuna Get By Naziv" id="d280580d-e0a7-4207-9aaa-c23c914a1112"><con:settings/><con:config service="http://localhost:8084" resourcePath="/tipRacunaNaziv/{naziv}" methodName="Method Get By Naziv" xsi:type="con:RestRequestStep" xmlns:xsi="http://www.w3.org/2001/XMLSchema-instance"><con:restRequest name="Tip Racuna Get By Naziv" id="17313365-ee72-4b2a-bffd-1db42ec4582e" mediaType="application/json"><con:settings><con:setting id="com.eviware.soapui.impl.wsdl.WsdlRequest@request-headers">&lt;xml-fragment/></con:setting></con:settings><con:endpoint>http://localhost:8084</con:endpoint><con:request/><con:originalUri>http://localhost/kredit/1</con:originalUri><con:assertion type="Valid HTTP Status Codes" id="0043dd5b-c60b-4c08-92bf-bc0ef47a123b" name="Valid HTTP Status Codes"><con:configuration><codes>200</codes></con:configuration></con:assertion><con:credentials><con:authType>No Authorization</con:authType></con:credentials><con:jmsConfig JMSDeliveryMode="PERSISTENT"/><con:jmsPropertyConfig/><con:parameters><entry key="naziv" value="Tekuci" xmlns="http://eviware.com/soapui/config"/></con:parameters><con:parameterOrder><con:entry>naziv</con:entry></con:parameterOrder></con:restRequest></con:config></con:testStep><con:testStep type="restrequest" name="Tip Racuna Insert" id="49986df9-0750-4d6d-b6b3-d4b4b24bbd3b"><con:settings/><con:config service="http://localhost:8084" resourcePath="/tipRacuna" methodName="Method Insert" xsi:type="con:RestRequestStep" xmlns:xsi="http://www.w3.org/2001/XMLSchema-instance"><con:restRequest name="Tip Racuna Insert" id="55b5b7b4-ab41-4887-bc57-ca7d68b59919" mediaType="application/json" postQueryString="false"><con:settings><con:setting id="com.eviware.soapui.impl.wsdl.WsdlRequest@request-headers">&lt;xml-fragment/></con:setting></con:settings><con:endpoint>http://localhost:8084</con:endpoint><con:request>{
      "id": -54,
      "naziv": "Insert",
      "opis": "Insert",
      "oznaka": "211"
   }</con:request><con:originalUri>http://localhost/kredit</con:originalUri><con:assertion type="Valid HTTP Status Codes" id="05434ec2-652b-4fcc-9088-1f71da83d67e" name="Valid HTTP Status Codes"><con:configuration><codes>200</codes></con:configuration></con:assertion><con:credentials><con:authType>No Authorization</con:authType></con:credentials><con:jmsConfig JMSDeliveryMode="PERSISTENT"/><con:jmsPropertyConfig/><con:parameters/></con:restRequest></con:config></con:testStep><con:testStep type="restrequest" name="Tip Racuna Update" id="285b4176-8217-44f0-a14d-f9d006616ccb"><con:settings/><con:config service="http://localhost:8084" resourcePath="/tipRacuna" methodName="Method Update" xsi:type="con:RestRequestStep" xmlns:xsi="http://www.w3.org/2001/XMLSchema-instance"><con:restRequest name="Tip Racuna Update" id="55b5b7b4-ab41-4887-bc57-ca7d68b59919" mediaType="application/json" postQueryString="false"><con:settings><con:setting id="com.eviware.soapui.impl.wsdl.WsdlRequest@request-headers">&lt;xml-fragment/></con:setting></con:settings><con:endpoint>http://localhost:8084</con:endpoint><con:request>{
      "id": -100,
      "naziv": "Update",
      "opis": "Update",
      "oznaka": "211"
   }</con:request><con:originalUri>http://localhost/kredit</con:originalUri><con:assertion type="Valid HTTP Status Codes" id="dd3331e6-12fd-405f-b4f2-bd7749274921" name="Valid HTTP Status Codes"><con:configuration><codes>200</codes></con:configuration></con:assertion><con:credentials><con:authType>No Authorization</con:authType></con:credentials><con:jmsConfig JMSDeliveryMode="PERSISTENT"/><con:jmsPropertyConfig/><con:parameters/></con:restRequest></con:config></con:testStep><con:testStep type="restrequest" name="Tip Racuna Delete" id="56bb89cf-c367-4951-8209-f983be9d4bc4"><con:settings/><con:config service="http://localhost:8084" resourcePath="/tipRacuna/{id}" methodName="Method Delete" xsi:type="con:RestRequestStep" xmlns:xsi="http://www.w3.org/2001/XMLSchema-instance"><con:restRequest name="Tip Racuna Delete" id="55b5b7b4-ab41-4887-bc57-ca7d68b59919" mediaType="application/json" postQueryString="false"><con:settings><con:setting id="com.eviware.soapui.impl.wsdl.WsdlRequest@request-headers">&lt;xml-fragment/></con:setting></con:settings><con:endpoint>http://localhost:8084</con:endpoint><con:request/><con:originalUri>http://localhost/kredit</con:originalUri><con:assertion type="Valid HTTP Status Codes" id="32591e96-df51-46b2-b448-032a32d3afd9" name="Valid HTTP Status Codes"><con:configuration><codes>200</codes></con:configuration></con:assertion><con:credentials><con:authType>No Authorization</con:authType></con:credentials><con:jmsConfig JMSDeliveryMode="PERSISTENT"/><con:jmsPropertyConfig/><con:parameters><entry key="id" value="-100" xmlns="http://eviware.com/soapui/config"/></con:parameters><con:parameterOrder><con:entry>id</con:entry></con:parameterOrder></con:restRequest></con:config></con:testStep><con:testStep type="restrequest" name="Klijent Get All" id="9ea24ab2-bc66-4e2b-b46d-eb40cac387cb"><con:settings/><con:config service="http://localhost:8084" resourcePath="/klijent" methodName="Get All" xsi:type="con:RestRequestStep" xmlns:xsi="http://www.w3.org/2001/XMLSchema-instance"><con:restRequest name="Klijent Get All" id="55b5b7b4-ab41-4887-bc57-ca7d68b59919" mediaType="application/json"><con:settings><con:setting id="com.eviware.soapui.impl.wsdl.WsdlRequest@request-headers">&lt;xml-fragment/></con:setting></con:settings><con:endpoint>http://localhost:8084</con:endpoint><con:request/><con:originalUri>http://localhost/kredit</con:originalUri><con:assertion type="Valid HTTP Status Codes" id="9167d3bf-d521-4d28-9afa-453dfb46c7ef" name="Valid HTTP Status Codes"><con:configuration><codes>200</codes></con:configuration></con:assertion><con:credentials><con:authType>No Authorization</con:authType></con:credentials><con:jmsConfig JMSDeliveryMode="PERSISTENT"/><con:jmsPropertyConfig/><con:parameters/></con:restRequest></con:config></con:testStep><con:testStep type="restrequest" name="Klijent Get By ID" id="3ab0ba96-d962-4acd-b0ce-43e6a9cb26c8"><con:settings/><con:config service="http://localhost:8084" resourcePath="/klijent/{id}" methodName="Method Get By ID" xsi:type="con:RestRequestStep" xmlns:xsi="http://www.w3.org/2001/XMLSchema-instance"><con:restRequest name="Klijent Get By ID" id="17313365-ee72-4b2a-bffd-1db42ec4582e" mediaType="application/json"><con:settings><con:setting id="com.eviware.soapui.impl.wsdl.WsdlRequest@request-headers">&lt;xml-fragment/></con:setting></con:settings><con:endpoint>http://localhost:8084</con:endpoint><con:request/><con:originalUri>http://localhost/kredit/1</con:originalUri><con:assertion type="Valid HTTP Status Codes" id="cc4ef148-dde2-44ab-863e-cb5c21048321" name="Valid HTTP Status Codes"><con:configuration><codes>200</codes></con:configuration></con:assertion><con:credentials><con:authType>No Authorization</con:authType></con:credentials><con:jmsConfig JMSDeliveryMode="PERSISTENT"/><con:jmsPropertyConfig/><con:parameters><entry key="id" value="1" xmlns="http://eviware.com/soapui/config"/></con:parameters><con:parameterOrder><con:entry>id</con:entry></con:parameterOrder></con:restRequest></con:config></con:testStep><con:testStep type="restrequest" name="Klijent Get By Kredit" id="043dd8f1-bdfe-44b6-adc6-a5084a0da7a9"><con:settings/><con:config service="http://localhost:8084" resourcePath="/klijentPoKreditu/{id}" methodName="Method Get By Kredit" xsi:type="con:RestRequestStep" xmlns:xsi="http://www.w3.org/2001/XMLSchema-instance"><con:restRequest name="Klijent Get By Kredit" id="17313365-ee72-4b2a-bffd-1db42ec4582e" mediaType="application/json"><con:settings><con:setting id="com.eviware.soapui.impl.wsdl.WsdlRequest@request-headers">&lt;xml-fragment/></con:setting></con:settings><con:endpoint>http://localhost:8084</con:endpoint><con:request/><con:originalUri>http://localhost/kredit/1</con:originalUri><con:assertion type="Valid HTTP Status Codes" id="20c54cfd-fac9-485e-9428-637182937c0b" name="Valid HTTP Status Codes"><con:configuration><codes>200</codes></con:configuration></con:assertion><con:credentials><con:authType>No Authorization</con:authType></con:credentials><con:jmsConfig JMSDeliveryMode="PERSISTENT"/><con:jmsPropertyConfig/><con:parameters><entry key="id" value="1" xmlns="http://eviware.com/soapui/config"/></con:parameters><con:parameterOrder><con:entry>id</con:entry></con:parameterOrder></con:restRequest></con:config></con:testStep><con:testStep type="restrequest" name="Klijent Insert" id="56bc5174-4d67-43a9-b903-aaa38d744149"><con:settings/><con:config service="http://localhost:8084" resourcePath="/klijent" methodName="Method Insert" xsi:type="con:RestRequestStep" xmlns:xsi="http://www.w3.org/2001/XMLSchema-instance"><con:restRequest name="Klijent Insert" id="55b5b7b4-ab41-4887-bc57-ca7d68b59919" mediaType="application/json" postQueryString="false"><con:settings><con:setting id="com.eviware.soapui.impl.wsdl.WsdlRequest@request-headers">&lt;xml-fragment/></con:setting></con:settings><con:endpoint>http://localhost:8084</con:endpoint><con:request>{
   "id": -45,
   "brojLk": 285937204,
   "ime": "Insert",
   "prezime": "Insert",
   "kredit":    {
      "id": 2,
      "naziv": "Stambeni",
      "opis": "Stambeni kredit je namenjen kupovini nekog stambenog objekta i formalno klijent postaje njegov vlasnik ali i u principu na taj stan se stavlja hipoteka u korist banke koja je odobrila kredit.",
      "oznaka": "2"
   }
}</con:request><con:originalUri>http://localhost/kredit</con:originalUri><con:assertion type="Valid HTTP Status Codes" id="9c4b5f8b-1803-44f7-96cc-ef0a5ece0837" name="Valid HTTP Status Codes"><con:configuration><codes>200</codes></con:configuration></con:assertion><con:credentials><con:authType>No Authorization</con:authType></con:credentials><con:jmsConfig JMSDeliveryMode="PERSISTENT"/><con:jmsPropertyConfig/><con:parameters/></con:restRequest></con:config></con:testStep><con:testStep type="restrequest" name="Klijent Update" id="ef5693e8-73c6-41df-9b23-76108c02097d"><con:settings/><con:config service="http://localhost:8084" resourcePath="/klijent" methodName="Method Update" xsi:type="con:RestRequestStep" xmlns:xsi="http://www.w3.org/2001/XMLSchema-instance"><con:restRequest name="Klijent Update" id="55b5b7b4-ab41-4887-bc57-ca7d68b59919" mediaType="application/json" postQueryString="false"><con:settings><con:setting id="com.eviware.soapui.impl.wsdl.WsdlRequest@request-headers">&lt;xml-fragment/></con:setting></con:settings><con:endpoint>http://localhost:8084</con:endpoint><con:request>{
   "id": -100,
   "brojLk": 285937204,
   "ime": "Update",
   "prezime": "Update",
   "kredit":    {
      "id": 2,
      "naziv": "Stambeni",
      "opis": "Stambeni kredit je namenjen kupovini nekog stambenog objekta i formalno klijent postaje njegov vlasnik ali i u principu na taj stan se stavlja hipoteka u korist banke koja je odobrila kredit.",
      "oznaka": "2"
   }
}</con:request><con:originalUri>http://localhost/kredit</con:originalUri><con:assertion type="Valid HTTP Status Codes" id="708cbef5-69f6-4490-9336-0219b27c0ae7" name="Valid HTTP Status Codes"><con:configuration><codes>200</codes></con:configuration></con:assertion><con:credentials><con:authType>No Authorization</con:authType></con:credentials><con:jmsConfig JMSDeliveryMode="PERSISTENT"/><con:jmsPropertyConfig/><con:parameters/></con:restRequest></con:config></con:testStep><con:testStep type="restrequest" name="Klijent Delete" id="262ee32a-be24-4eec-8e12-73801eb9c7e2"><con:settings/><con:config service="http://localhost:8084" resourcePath="/klijent/{id}" methodName="Method Delete" xsi:type="con:RestRequestStep" xmlns:xsi="http://www.w3.org/2001/XMLSchema-instance"><con:restRequest name="Klijent Delete" id="55b5b7b4-ab41-4887-bc57-ca7d68b59919" mediaType="application/json" postQueryString="false"><con:settings><con:setting id="com.eviware.soapui.impl.wsdl.WsdlRequest@request-headers">&lt;xml-fragment/></con:setting></con:settings><con:endpoint>http://localhost:8084</con:endpoint><con:request/><con:originalUri>http://localhost/kredit</con:originalUri><con:assertion type="Valid HTTP Status Codes" id="eee020f2-46f8-487f-a7ec-263d4668606d" name="Valid HTTP Status Codes"><con:configuration><codes>200</codes></con:configuration></con:assertion><con:credentials><con:authType>No Authorization</con:authType></con:credentials><con:jmsConfig JMSDeliveryMode="PERSISTENT"/><con:jmsPropertyConfig/><con:parameters/><con:parameterOrder><con:entry>id</con:entry></con:parameterOrder></con:restRequest></con:config></con:testStep><con:testStep type="restrequest" name="Racun Get By Tip Racuna" id="f98292d9-2159-4f73-8393-8e83129e6db7"><con:settings/><con:config service="http://localhost:8084" resourcePath="/racunPoTipuRacuna/{id}" methodName="Method Get By Tip Racuna" xsi:type="con:RestRequestStep" xmlns:xsi="http://www.w3.org/2001/XMLSchema-instance"><con:restRequest name="Racun Get By Tip Racuna" id="17313365-ee72-4b2a-bffd-1db42ec4582e" mediaType="application/json"><con:settings><con:setting id="com.eviware.soapui.impl.wsdl.WsdlRequest@request-headers">&lt;xml-fragment/></con:setting></con:settings><con:endpoint>http://localhost:8084</con:endpoint><con:request/><con:originalUri>http://localhost/kredit/1</con:originalUri><con:assertion type="Valid HTTP Status Codes" id="23d11778-fe19-46b7-8b1c-4a478bfe28d6" name="Valid HTTP Status Codes"><con:configuration><codes>200</codes></con:configuration></con:assertion><con:credentials><con:authType>No Authorization</con:authType></con:credentials><con:jmsConfig JMSDeliveryMode="PERSISTENT"/><con:jmsPropertyConfig/><con:parameters><entry key="id" value="1" xmlns="http://eviware.com/soapui/config"/></con:parameters><con:parameterOrder><con:entry>id</con:entry></con:parameterOrder></con:restRequest></con:config></con:testStep><con:testStep type="restrequest" name="Racun Get By Klijent" id="5f45ffa6-c94c-4dfd-89ce-702d3b34a76c"><con:settings/><con:config service="http://localhost:8084" resourcePath="/racunPoKlijentu/{id}" methodName="Method Get By Klijent" xsi:type="con:RestRequestStep" xmlns:xsi="http://www.w3.org/2001/XMLSchema-instance"><con:restRequest name="Racun Get By Klijent" id="17313365-ee72-4b2a-bffd-1db42ec4582e" mediaType="application/json"><con:settings><con:setting id="com.eviware.soapui.impl.wsdl.WsdlRequest@request-headers">&lt;xml-fragment/></con:setting></con:settings><con:endpoint>http://localhost:8084</con:endpoint><con:request/><con:originalUri>http://localhost/kredit/1</con:originalUri><con:assertion type="Valid HTTP Status Codes" id="48d7db52-132e-4ace-811f-fb63be6a3f60" name="Valid HTTP Status Codes"><con:configuration><codes>200</codes></con:configuration></con:assertion><con:credentials><con:authType>No Authorization</con:authType></con:credentials><con:jmsConfig JMSDeliveryMode="PERSISTENT"/><con:jmsPropertyConfig/><con:parameters><entry key="id" value="1" xmlns="http://eviware.com/soapui/config"/></con:parameters><con:parameterOrder><con:entry>id</con:entry></con:parameterOrder></con:restRequest></con:config></con:testStep><con:testStep type="restrequest" name="Racun Get All" id="96fd730b-9426-4bee-8a39-cb8d00ae8b0a"><con:settings/><con:config service="http://localhost:8084" resourcePath="/racun" methodName="Get All" xsi:type="con:RestRequestStep" xmlns:xsi="http://www.w3.org/2001/XMLSchema-instance"><con:restRequest name="Racun Get All" id="55b5b7b4-ab41-4887-bc57-ca7d68b59919" mediaType="application/json"><con:settings><con:setting id="com.eviware.soapui.impl.wsdl.WsdlRequest@request-headers">&lt;xml-fragment/></con:setting></con:settings><con:endpoint>http://localhost:8084</con:endpoint><con:request/><con:originalUri>http://localhost/kredit</con:originalUri><con:assertion type="Valid HTTP Status Codes" id="b2221925-baf6-4404-ad53-185f6bf7e8e3" name="Valid HTTP Status Codes"><con:configuration><codes>200</codes></con:configuration></con:assertion><con:credentials><con:authType>No Authorization</con:authType></con:credentials><con:jmsConfig JMSDeliveryMode="PERSISTENT"/><con:jmsPropertyConfig/><con:parameters/></con:restRequest></con:config></con:testStep><con:testStep type="restrequest" name="Racun Get By ID" id="82961e32-f1b8-4897-8fc6-a3f89821131d"><con:settings/><con:config service="http://localhost:8084" resourcePath="/racun/{id}" methodName="Method Get By ID" xsi:type="con:RestRequestStep" xmlns:xsi="http://www.w3.org/2001/XMLSchema-instance"><con:restRequest name="Racun Get By ID" id="17313365-ee72-4b2a-bffd-1db42ec4582e" mediaType="application/json"><con:settings><con:setting id="com.eviware.soapui.impl.wsdl.WsdlRequest@request-headers">&lt;xml-fragment/></con:setting></con:settings><con:endpoint>http://localhost:8084</con:endpoint><con:request/><con:originalUri>http://localhost/kredit/1</con:originalUri><con:assertion type="Valid HTTP Status Codes" id="0e6bacad-e125-4898-8b48-0ec2f97a7e53" name="Valid HTTP Status Codes"><con:configuration><codes>200</codes></con:configuration></con:assertion><con:credentials><con:authType>No Authorization</con:authType></con:credentials><con:jmsConfig JMSDeliveryMode="PERSISTENT"/><con:jmsPropertyConfig/><con:parameters><entry key="id" value="1" xmlns="http://eviware.com/soapui/config"/></con:parameters><con:parameterOrder><con:entry>id</con:entry></con:parameterOrder></con:restRequest></con:config></con:testStep><con:testStep type="restrequest" name="Racun Insert" id="7f41e2da-0942-4cb5-a164-03e82f1be0c8"><con:settings/><con:config service="http://localhost:8084" resourcePath="/racun" methodName="Method Insert" xsi:type="con:RestRequestStep" xmlns:xsi="http://www.w3.org/2001/XMLSchema-instance"><con:restRequest name="Racun Insert" id="55b5b7b4-ab41-4887-bc57-ca7d68b59919" mediaType="application/json" postQueryString="false"><con:settings><con:setting id="com.eviware.soapui.impl.wsdl.WsdlRequest@request-headers">&lt;xml-fragment/></con:setting></con:settings><con:endpoint>http://localhost:8084</con:endpoint><con:request>{
   "id": -45,
   "naziv": "Insert",
   "opis": "Insert",
   "oznaka": "1",
   "klijent":    {
      "id": 4,
      "brojLk": 985648276,
      "ime": "Luka",
      "prezime": "Lukic",
      "kredit":       {
         "id": 3,
         "naziv": "Studentski",
         "opis": "Studentski kredit je namenjen samo i iskljucivo studentima i koristi se za finansiranje studija ili studentskih potreba poput placanja smestaja i hrane u studentskim domovima",
         "oznaka": "3"
      }
   },
   "tipRacuna":    {
      "id": 1,
      "naziv": "Tekuci",
      "opis": "Racun na temelju kojega se mogu uzimati cekovi i dogovoriti PREKORACENJE. Tekuci racuni obicno ne nose znatnije iznose KAMATA na pozitivna salda",
      "oznaka": "1"
   }
}</con:request><con:originalUri>http://localhost/kredit</con:originalUri><con:assertion type="Valid HTTP Status Codes" id="b7876c6e-f7c4-4fb9-afb0-450e93230a28" name="Valid HTTP Status Codes"><con:configuration><codes>200</codes></con:configuration></con:assertion><con:credentials><con:authType>No Authorization</con:authType></con:credentials><con:jmsConfig JMSDeliveryMode="PERSISTENT"/><con:jmsPropertyConfig/><con:parameters/></con:restRequest></con:config></con:testStep><con:testStep type="restrequest" name="Racun Update" id="c3fee026-be07-48cd-916a-b837fed68f27"><con:settings/><con:config service="http://localhost:8084" resourcePath="/racun" methodName="Method Update" xsi:type="con:RestRequestStep" xmlns:xsi="http://www.w3.org/2001/XMLSchema-instance"><con:restRequest name="Racun Update" id="55b5b7b4-ab41-4887-bc57-ca7d68b59919" mediaType="application/json" postQueryString="false"><con:settings><con:setting id="com.eviware.soapui.impl.wsdl.WsdlRequest@request-headers">&lt;xml-fragment/></con:setting></con:settings><con:endpoint>http://localhost:8084</con:endpoint><con:request>{
   "id": -100,
   "naziv": "update",
   "opis": "update",
   "oznaka": "1",
   "klijent":    {
      "id": 4,
      "brojLk": 985648276,
      "ime": "Luka",
      "prezime": "Lukic",
      "kredit":       {
         "id": 3,
         "naziv": "Studentski",
         "opis": "Studentski kredit je namenjen samo i iskljucivo studentima i koristi se za finansiranje studija ili studentskih potreba poput placanja smestaja i hrane u studentskim domovima",
         "oznaka": "3"
      }
   },
   "tipRacuna":    {
      "id": 1,
      "naziv": "Tekuci",
      "opis": "Racun na temelju kojega se mogu uzimati cekovi i dogovoriti PREKORACENJE. Tekuci racuni obicno ne nose znatnije iznose KAMATA na pozitivna salda",
      "oznaka": "1"
   }
}</con:request><con:originalUri>http://localhost/kredit</con:originalUri><con:assertion type="Valid HTTP Status Codes" id="6a5716a1-fb90-4c8f-a5f8-4344798546b8" name="Valid HTTP Status Codes"><con:configuration><codes>200</codes></con:configuration></con:assertion><con:credentials><con:authType>No Authorization</con:authType></con:credentials><con:jmsConfig JMSDeliveryMode="PERSISTENT"/><con:jmsPropertyConfig/><con:parameters/><con:parameterOrder/></con:restRequest></con:config></con:testStep><con:testStep type="restrequest" name="Racun Delete" id="44cc0dc5-0b73-4581-9519-9ef3c43102fb"><con:settings/><con:config service="http://localhost:8084" resourcePath="/kredit/{id}" methodName="Method Delete" xsi:type="con:RestRequestStep" xmlns:xsi="http://www.w3.org/2001/XMLSchema-instance"><con:restRequest name="Racun Delete" id="55b5b7b4-ab41-4887-bc57-ca7d68b59919" mediaType="application/json" postQueryString="false"><con:settings><con:setting id="com.eviware.soapui.impl.wsdl.WsdlRequest@request-headers">&lt;xml-fragment/></con:setting></con:settings><con:endpoint>http://localhost:8084</con:endpoint><con:request/><con:originalUri>http://localhost/kredit</con:originalUri><con:assertion type="Valid HTTP Status Codes" id="68e57c4f-e9b1-48a5-9962-67bac0386539" name="Valid HTTP Status Codes"><con:configuration><codes>200</codes></con:configuration></con:assertion><con:credentials><con:authType>No Authorization</con:authType></con:credentials><con:jmsConfig JMSDeliveryMode="PERSISTENT"/><con:jmsPropertyConfig/><con:parameters><entry key="id" value="-100" xmlns="http://eviware.com/soapui/config"/></con:parameters><con:parameterOrder><con:entry>id</con:entry></con:parameterOrder></con:restRequest></con:config></con:testStep><con:properties/></con:testCase><con:properties/></con:testSuite><con:properties/><con:wssContainer/><con:oAuth2ProfileContainer/><con:oAuth1ProfileContainer/><con:sensitiveInformation/></con:soapui-project>